vibethon_cli.py
vibethon/__init__.py
vibethon/__main__.py
vibethon/llm.py
vibethon/models.py
vibethon/vdb.py
vibethon/vibezz.py
vibethon-1.0.1.dist-info/licenses/LICENSE
vibethon-1.0.1.dist-info/METADATA
vibethon-1.0.1.dist-info/WHEEL
vibethon-1.0.1.dist-info/entry_points.txt
vibethon-1.0.1.dist-info/top_level.txt
vibethon-1.0.1.dist-info/RECORD
