Metadata-Version: 2.4
Name: vibethon
Version: 1.0.1
Summary: Automatic Python Debugger with LLM-powered Interactive REPL
Home-page: https://github.com/ennucore/vibethon
Author: Guillermo Valle Perez, Joshua Harry
Author-email: Lev Chizhov <lc@lev.la>
License: MIT License
Project-URL: Homepage, https://github.com/ennucore/vibethon
Project-URL: Repository, https://github.com/ennucore/vibethon
Project-URL: Issues, https://github.com/ennucore/vibethon/issues
Classifier: Development Status :: 4 - Beta
Classifier: Intended Audience :: Developers
Classifier: License :: OSI Approved :: MIT License
Classifier: Programming Language :: Python :: 3
Classifier: Programming Language :: Python :: 3.8
Classifier: Programming Language :: Python :: 3.9
Classifier: Programming Language :: Python :: 3.10
Classifier: Programming Language :: Python :: 3.11
Classifier: Programming Language :: Python :: 3.12
Classifier: Topic :: Software Development :: Debuggers
Requires-Python: >=3.6
License-File: LICENSE
Requires-Dist: openai>=1.0.0
Requires-Dist: httpx>=0.24.0
Requires-Dist: pydantic>=2.0.0
Dynamic: home-page
Dynamic: license-file
Dynamic: requires-python
